MANIFEST.in
README.rst
setup.py
django_ws4ever/__init__.py
django_ws4ever/settings.py
django_ws4ever/urls.py
django_ws4ever/views.py
django_ws4ever/wsgi.py
django_ws4ever.egg-info/PKG-INFO
django_ws4ever.egg-info/SOURCES.txt
django_ws4ever.egg-info/dependency_links.txt
django_ws4ever.egg-info/requires.txt
django_ws4ever.egg-info/top_level.txt
ws4ever/__init__.py
ws4ever/apps.py
ws4ever/backend.py
ws4ever/helpers.py
ws4ever/tests.py
ws4ever/views.py
ws4ever/management/__init__.py
ws4ever/management/commands/__init__.py
ws4ever/management/commands/broadcast.py
ws4ever/management/commands/runserver.py
ws4ever/migrations/__init__.py